opscore/__init__.py
opscore/RO/AddCallback.py
opscore/RO/BitDescr.py
opscore/RO/CanvasUtil.py
opscore/RO/CnvUtil.py
opscore/RO/Constants.py
opscore/RO/CoordSys.py
opscore/RO/DS9.py
opscore/RO/InputCont.py
opscore/RO/KeyDispatcher.py
opscore/RO/KeyVariable.py
opscore/RO/LangUtil.py
opscore/RO/MathUtil.py
opscore/RO/PVT.py
opscore/RO/PhysConst.py
opscore/RO/SQLUtil.py
opscore/RO/ScriptRunner.py
opscore/RO/SeqUtil.py
opscore/RO/StringUtil.py
opscore/RO/SysConst.py
opscore/RO/TkUtil.py
opscore/RO/Version.py
opscore/RO/__init__.py
opscore/RO/procFiles.py
opscore/RO/Alg/GenericCallback.py
opscore/RO/Alg/IDGen.py
opscore/RO/Alg/ListPlus.py
opscore/RO/Alg/MatchList.py
opscore/RO/Alg/MultiDict.py
opscore/RO/Alg/MultiListIter.py
opscore/RO/Alg/OrderedDict.py
opscore/RO/Alg/RandomWalk.py
opscore/RO/Alg/SavedDict.py
opscore/RO/Alg/__init__.py
opscore/RO/Astro/ImageWindow.py
opscore/RO/Astro/__init__.py
opscore/RO/Astro/runTests.py
opscore/RO/Astro/Cnv/AppGeoData.py
opscore/RO/Astro/Cnv/AzAltFromHADec.py
opscore/RO/Astro/Cnv/CoordConv.py
opscore/RO/Astro/Cnv/FK4FromICRS.py
opscore/RO/Astro/Cnv/FK5Prec.py
opscore/RO/Astro/Cnv/GalFromICRS.py
opscore/RO/Astro/Cnv/GeoFromICRS.py
opscore/RO/Astro/Cnv/GeoFromTopo.py
opscore/RO/Astro/Cnv/HADecFromAzAlt.py
opscore/RO/Astro/Cnv/ICRSFromFK4.py
opscore/RO/Astro/Cnv/ICRSFromFixedFK4.py
opscore/RO/Astro/Cnv/ICRSFromGal.py
opscore/RO/Astro/Cnv/ICRSFromGeo.py
opscore/RO/Astro/Cnv/ObsFromTopo.py
opscore/RO/Astro/Cnv/ObserverData.py
opscore/RO/Astro/Cnv/TopoFromGeo.py
opscore/RO/Astro/Cnv/TopoFromGeoSimple.py
opscore/RO/Astro/Cnv/TopoFromObs.py
opscore/RO/Astro/Cnv/__init__.py
opscore/RO/Astro/Sph/Airmass.py
opscore/RO/Astro/Sph/AngSep.py
opscore/RO/Astro/Sph/AngSideAng.py
opscore/RO/Astro/Sph/AzAltFromHADec.py
opscore/RO/Astro/Sph/CCFromSC.py
opscore/RO/Astro/Sph/CCFromSCPV.py
opscore/RO/Astro/Sph/CCFromSCPVOff.py
opscore/RO/Astro/Sph/Const.py
opscore/RO/Astro/Sph/CoordConv.py
opscore/RO/Astro/Sph/DCFromSC.py
sdss_opscore-3.0.4.dist-info/LICENSE.md
sdss_opscore-3.0.4.dist-info/METADATA
sdss_opscore-3.0.4.dist-info/WHEEL
sdss_opscore-3.0.4.dist-info/top_level.txt
sdss_opscore-3.0.4.dist-info/RECORD
