Metadata-Version: 2.1
Name: sdss-opscore
Version: 3.0.4
Summary: SDSS core actor and parsing classes
Home-page: https://github.com/sdss/opscore
Author: David Kirkby
Author-email: dkirkby@uci.edu
Maintainer: José Sánchez-Gallego
Maintainer-email: gallegoj@uw.edu
License: BSD 3-Clause License
Project-URL: Repository, https://github.com/sdss/opscore
Keywords: astronomy,software
Platform: UNKNOWN
Classifier: Intended Audience :: Science/Research
Classifier: Natural Language :: English
Classifier: Operating System :: OS Independent
Classifier: Programming Language :: Python
Classifier: Programming Language :: Python :: 3.6
Classifier: Programming Language :: Python :: 3.7
Classifier: Topic :: Software Development :: Libraries :: Python Modules
Requires-Python: >=3.7
License-File: LICENSE.md
Requires-Dist: numpy (>=1.21.1)
Requires-Dist: twisted (>=21.7.0)
Provides-Extra: dev
Requires-Dist: black ; extra == 'dev'
Requires-Dist: flake8 ; extra == 'dev'
Requires-Dist: sdsstools ; extra == 'dev'
Requires-Dist: twine ; extra == 'dev'
Requires-Dist: wheel ; extra == 'dev'
